{
  "@type": "WillRegistry",
  "testator": "Yuki Hamada (Enabler Inc.)",
  "versions": [
    {
      "version": "1.0.0-draft",
      "issued_at": "2026-05-18T16:00:00+09:00",
      "legal_status": "draft_付言事項のみ_法的拘束力なし",
      "sha256": "071f3f77ba04b484478d67cd31032ee61d482b259f42c7927378354ad26add64",
      "size_bytes": 3450,
      "anchors": {
        "solana_memo": "https://solscan.io/tx/2JsjC4vvG9CaYH2HYhNGPuNQ8edQBM4cSpQAWe7UdejTD86G4wvWJGBDFkzJMyLRz7KxMv9egPb1c8HpzrgXZYar",
        "bitcoin_ots": "./v1.0.0-draft.json.ots"
      },
      "json_url": "https://wearmu.com/will/v1.0.0-draft.json",
      "canonical_url": "https://wearmu.com/will/v1.0.0-draft.canonical.json",
      "hash_url": "https://wearmu.com/will/v1.0.0-draft.sha256"
    }
  ],
  "current": "1.0.0-draft",
  "verification_cmd": "curl https://wearmu.com/will/v1.0.0-draft.json | python3 -c 'import sys,json,hashlib;d=json.load(sys.stdin);c=json.dumps(d,ensure_ascii=False,sort_keys=True,separators=(\",\",\":\")).encode();print(hashlib.sha256(c).hexdigest())'"
}